mlserver_huggingface_striveworks/__init__.py
mlserver_huggingface_striveworks/codecs/__init__.py
mlserver_huggingface_striveworks/codecs/base.py
mlserver_huggingface_striveworks/codecs/conversation.py
mlserver_huggingface_striveworks/codecs/image.py
mlserver_huggingface_striveworks/codecs/json.py
mlserver_huggingface_striveworks/codecs/jsonlist.py
mlserver_huggingface_striveworks/codecs/numpylist.py
mlserver_huggingface_striveworks/codecs/raw.py
mlserver_huggingface_striveworks/codecs/utils.py
mlserver_huggingface_striveworks/common.py
mlserver_huggingface_striveworks/errors.py
mlserver_huggingface_striveworks/metadata.py
mlserver_huggingface_striveworks/runtime.py
mlserver_huggingface_striveworks/settings.py
mlserver_huggingface_striveworks/version.py
mlserver_huggingface_striveworks-1.4.0.dev3.dist-info/LICENSE
mlserver_huggingface_striveworks-1.4.0.dev3.dist-info/METADATA
mlserver_huggingface_striveworks-1.4.0.dev3.dist-info/WHEEL
mlserver_huggingface_striveworks-1.4.0.dev3.dist-info/RECORD
