Metadata-Version: 2.1
Name: mlserver-huggingface-striveworks
Version: 1.4.0.dev3
Summary: HuggingFace runtime for MLServer
License: Apache-2.0
Author: Seldon Technologies Ltd.
Author-email: hello@seldon.io
Requires-Python: >=3.8.1,<3.12
Classifier: License :: OSI Approved :: Apache Software License
Classifier: Programming Language :: Python :: 3
Classifier: Programming Language :: Python :: 3.9
Classifier: Programming Language :: Python :: 3.10
Classifier: Programming Language :: Python :: 3.11
Requires-Dist: mlserver
Requires-Dist: optimum[onnxruntime] (>=1.4,<2.0)
Requires-Dist: pillow
Requires-Dist: tensorflow
